task_weaver/__init__.py
task_weaver/config.py
task_weaver/exceptions.py
task_weaver/core/program_info.py
task_weaver/core/server.py
task_weaver/core/task.py
task_weaver/core/task_catalog.py
task_weaver/log/logger.py
task_weaver/models/__init__.py
task_weaver/models/server_models.py
task_weaver/models/task_models.py
task_weaver/utils/__init__.py
task_weaver/utils/cache.py
task_weaver-0.2.1.dist-info/METADATA
task_weaver-0.2.1.dist-info/WHEEL
task_weaver-0.2.1.dist-info/licenses/LICENSE
task_weaver-0.2.1.dist-info/RECORD
