Metadata-Version: 2.3
Name: task-weaver
Version: 0.2.1
Summary: A flexible task scheduling and server management library
Project-URL: Homepage, https://github.com/creeponsky/task-weaver
Project-URL: Documentation, https://task-weaver.readthedocs.io/
Project-URL: Repository, https://github.com/creeponsky/task-weaver.git
Author-email: creeponsky <wenhaozuo1@gmail.com>
Classifier: License :: OSI Approved :: MIT License
Classifier: Operating System :: OS Independent
Classifier: Programming Language :: Python :: 3
Classifier: Programming Language :: Python :: 3.10
Requires-Python: >=3.10
Requires-Dist: annotated-types>=0.7.0
Requires-Dist: anyio>=4.6.2
Requires-Dist: certifi>=2024.8.30
Requires-Dist: httpcore>=1.0.6
Requires-Dist: httpx>=0.27.2
Requires-Dist: idna>=3.10
Requires-Dist: pydantic-core>=2.23.4
Requires-Dist: pydantic>=2.9.2
Requires-Dist: sniffio>=1.3.1
Requires-Dist: typing-extensions>=4.12.2
Provides-Extra: test
Requires-Dist: click>=8.1.7; extra == 'test'
Requires-Dist: colorama>=0.4.6; extra == 'test'
Requires-Dist: exceptiongroup>=1.2.2; extra == 'test'
Requires-Dist: fastapi>=0.115.4; extra == 'test'
Requires-Dist: h11>=0.14.0; extra == 'test'
Requires-Dist: iniconfig>=2.0.0; extra == 'test'
Requires-Dist: packaging>=24.1; extra == 'test'
Requires-Dist: pluggy>=1.5.0; extra == 'test'
Requires-Dist: pytest-asyncio>=0.24.0; extra == 'test'
Requires-Dist: pytest>=8.3.3; extra == 'test'
Requires-Dist: starlette>=0.41.2; extra == 'test'
Requires-Dist: tomli>=2.0.2; extra == 'test'
Requires-Dist: uvicorn>=0.32.0; extra == 'test'
